{"elapsed":"0.256","endpoint-url":"https://raw.githubusercontent.com/digital-land/development-plan-document-collection/main/data/southwark-development-plan-document.csv","entry-date":"2022-02-09T00:21:25.964577","request-headers":{"Accept":"*/*","Accept-Encoding":"gzip, deflate","Connection":"keep-alive","User-Agent":"DLUHC Digital Land"},"resource":"d949e93c7f803360311208c92f9246584389e13cb7010fc7d06879b87ea758e7","response-headers":{"Accept-Ranges":"bytes","Access-Control-Allow-Origin":"*","Cache-Control":"max-age=300","Connection":"keep-alive","Content-Encoding":"gzip","Content-Length":"3217","Content-Security-Policy":"default-src 'none'; style-src 'unsafe-inline'; sandbox","Content-Type":"text/plain; charset=utf-8","Date":"Wed, 09 Feb 2022 00:21:26 GMT","ETag":"W/\"c46e9d9ec7381d7f385f1657d0222e15fb5ab5a0f78ffc5db6a5c0da3e27da8c\"","Expires":"Wed, 09 Feb 2022 00:26:26 GMT","Source-Age":"0","Strict-Transport-Security":"max-age=31536000","Vary":"Authorization,Accept-Encoding,Origin","Via":"1.1 varnish","X-Cache":"MISS","X-Cache-Hits":"0","X-Content-Type-Options":"nosniff","X-Fastly-Request-ID":"a1e95019c93d70a2081ab8d1998a5111059220b5","X-Frame-Options":"deny","X-GitHub-Request-Id":"0F7E:03EA:3F3B86:4ED75C:62030906","X-Served-By":"cache-iad-kiad7000155-IAD","X-Timer":"S1644366086.474606,VS0,VE246","X-XSS-Protection":"1; mode=block"},"ssl-verify":true,"status":"200"}