{"elapsed":"0.532","endpoint-url":"https://raw.githubusercontent.com/digital-land/development-plan-document-collection/main/data/mineral-waste-plans-20210921.csv","entry-date":"2022-04-21T00:04:06.705192","request-headers":{"Accept":"*/*","Accept-Encoding":"gzip, deflate","Connection":"keep-alive","User-Agent":"DLUHC Digital Land"},"resource":"8f0ae171c5207fcf2912950740017578b0084a636371853daffffe2ba102fcd4","response-headers":{"Accept-Ranges":"bytes","Access-Control-Allow-Origin":"*","Cache-Control":"max-age=300","Connection":"keep-alive","Content-Encoding":"gzip","Content-Length":"5068","Content-Security-Policy":"default-src 'none'; style-src 'unsafe-inline'; sandbox","Content-Type":"text/plain; charset=utf-8","Date":"Thu, 21 Apr 2022 00:04:08 GMT","ETag":"W/\"3bab1d047884a2f544d7b05114f0cd090b3b7ff34206798c0fd12dc591fcde24\"","Expires":"Thu, 21 Apr 2022 00:09:08 GMT","Source-Age":"0","Strict-Transport-Security":"max-age=31536000","Vary":"Authorization,Accept-Encoding,Origin","Via":"1.1 varnish","X-Cache":"MISS","X-Cache-Hits":"0","X-Content-Type-Options":"nosniff","X-Fastly-Request-ID":"37b102d97ac7ba38d9e7be76c86b61048a983450","X-Frame-Options":"deny","X-GitHub-Request-Id":"BE10:66AE:715E0:BA3A7:62609F77","X-Served-By":"cache-iad-kiad7000051-IAD","X-Timer":"S1650499448.584715,VS0,VE527","X-XSS-Protection":"1; mode=block"},"ssl-verify":true,"status":"200"}